setup.py
backend/__init__.py
backend/base.py
backend/jiasheng.py
backend/unidata.py
python_backend.egg-info/PKG-INFO
python_backend.egg-info/SOURCES.txt
python_backend.egg-info/dependency_links.txt
python_backend.egg-info/not-zip-safe
python_backend.egg-info/requires.txt
python_backend.egg-info/top_level.txt