Metadata-Version: 1.0
Name: python-backend
Version: 0.0.1
Summary: Backend for Python
Home-page: UNKNOWN
Author: zwczou
Author-email: zwczou@gmail.com
License: BSD
Keywords: backend
Platform: any
